{"version":1,"resource":"file:///e%3A/Ahasoft/ahaplus-shop/Application/VueJS/src/pages/report/report-operational-trend-analysis/partials/section-overall-revenue/overall-revenue-chart-right.vue","entries":[{"id":"RnAB.vue","source":"Undo Create Diff","timestamp":1767670367510},{"id":"6gee.vue","source":"Workspace Edit","timestamp":1767671675089},{"id":"d4DD.vue","timestamp":1767671758262},{"id":"sdn6.vue","source":"Undo Create Diff","timestamp":1767672335625},{"id":"JYhL.vue","source":"Undo Chain Diff","timestamp":1767672349191},{"id":"oyYY.vue","timestamp":1767673268392},{"id":"I6PY.vue","source":"Fix all fixable ESLint issues","timestamp":1767673621955},{"id":"Zxcw.vue","source":"Fix all fixable ESLint issues","timestamp":1767673635116},{"id":"1uhL.vue","source":"Fix all fixable ESLint issues","timestamp":1767673660674},{"id":"ybfW.vue","timestamp":1767673783156},{"id":"gxME.vue","source":"undoRedo.source","timestamp":1767673803394},{"id":"O4qF.vue","timestamp":1767673924571},{"id":"0Bl5.vue","source":"Undo Create Diff","timestamp":1767674902680},{"id":"Zkwb.vue","timestamp":1767675225271},{"id":"4Nos.vue","timestamp":1767680306068},{"id":"5a8A.vue","timestamp":1767680328088},{"id":"rowZ.vue","source":"Fix all fixable ESLint issues","timestamp":1767680574058},{"id":"VC8L.vue","source":"Fix all fixable ESLint issues","timestamp":1767680630515},{"id":"b9TY.vue","timestamp":1767680701668},{"id":"fLsh.vue","timestamp":1767680728406},{"id":"OKYv.vue","timestamp":1767680752388},{"id":"Etyj.vue","timestamp":1767680789032},{"id":"RRad.vue","timestamp":1767680846561},{"id":"V1uL.vue","timestamp":1767680936092},{"id":"zwvC.vue","timestamp":1767680977395},{"id":"2HD8.vue","timestamp":1767683464639},{"id":"Z5YB.vue","timestamp":1767683492658},{"id":"gVnW.vue","timestamp":1767683554503},{"id":"2EB2.vue","timestamp":1767683847982},{"id":"bFlI.vue","source":"Undo Create Diff","timestamp":1767684791463},{"id":"Q9zP.vue","source":"Undo Chain Diff","timestamp":1767684800240},{"id":"yDw9.vue","source":"Undo Chain Diff","timestamp":1767684811830},{"id":"2y5f.vue","source":"Undo Accept Partial Diff","timestamp":1767684908616}]}